{
  "step_index": 1662,
  "tool_name": "replace_file_content",
  "arguments": {
    "AllowMultiple": "false",
    "Description": "\"Append 48 new tool detail views and helper methods to the end of _ToolDetailScreenState class.\"",
    "EndLine": "2145",
    "Instruction": "\"Replace the closing lines of the file to append the new methods for all the newly added tools.\"",
    "ReplacementContent": "\"    );\\n  }\\n\\n  // Content Helpers\\n  Widget _buildInfoSection(String title, String subtitle, String content) {\\n    return SingleChildScrollView(\\n      child: Card(\\n        elevation: 1.5,\\n        shape: RoundedRectangleBorder(borderRadius: BorderRadius.circular(16)),\\n        child: Padding(\\n          padding: const EdgeInsets.all(16.0),\\n          child: Column(\\n            crossAxisAlignment: CrossAxisAlignment.start,\\n            children: [\\n              Text(title, style: const TextStyle(fontWeight: FontWeight.bold, fontSize: 16, color: Color(0xFF1E5E43))),\\n              if (subtitle.isNotEmpty) ...[\\n                const SizedBox(height: 4),\\n                Text(subtitle, style: const TextStyle(fontSize: 12, color: Colors.grey, fontStyle: FontStyle.italic)),\\n              ],\\n              const Divider(height: 16),\\n              Text(content, style: const TextStyle(fontSize: 13, height: 1.45, color: Colors.black87)),\\n            ],\\n          ),\\n        ),\\n      ),\\n    );\\n  }\\n\\n  Widget _buildStepRehberi(String title, List<Map<String, String>> steps) {\\n    return Column(\\n      crossAxisAlignment: CrossAxisAlignment.start,\\n      children: [\\n        Text(title, style: const TextStyle(fontSize: 16, fontWeight: FontWeight.bold, color: Color(0xFF1E5E43))),\\n        const SizedBox(height: 12),\\n        Expanded(\\n          child: ListView.builder(\\n            itemCount: steps.length,\\n            itemBuilder: (context, index) {\\n              final step = steps[index];\\n              return Card(\\n                elevation: 1,\\n                shape: RoundedRectangleBorder(borderRadius: BorderRadius.circular(14)),\\n                margin: const EdgeInsets.only(bottom: 10),\\n                child: Padding(\\n                  padding: const EdgeInsets.all(14.0),\\n                  child: Row(\\n                    crossAxisAlignment: CrossAxisAlignment.start,\\n                    children: [\\n                      CircleAvatar(\\n                        radius: 14,\\n                        \n<truncated 61361 bytes>",
    "StartLine": "2143",
    "TargetContent": "\"    );\\n  }\\n}\"",
    "TargetFile": "\"c:\\\\Users\\\\kral_\\\\Namaz vakitleri\\\\namaz_app\\\\lib\\\\screens\\\\tool_detail_screen.dart\"",
    "toolAction": "\"Appending new tools details to tool_detail_screen.dart\"",
    "toolSummary": "\"Appending new tool detail views\""
  }
}